{
  "hash": "9468bff6",
  "configHash": "2169966c",
  "lockfileHash": "910b7c82",
  "browserHash": "20714367",
  "optimized": {
    "react/jsx-dev-runtime": {
      "src": "../../node_modules/react/jsx-dev-runtime.js",
      "file": "react_jsx-dev-runtime.js",
      "fileHash": "411a76f6",
      "needsInterop": true
    },
    "react": {
      "src": "../../node_modules/react/index.js",
      "file": "react.js",
      "fileHash": "9ac01a0c",
      "needsInterop": true
    },
    "react-dom/client": {
      "src": "../../node_modules/react-dom/client.js",
      "file": "react-dom_client.js",
      "fileHash": "9ba0cf6e",
      "needsInterop": true
    },
    "react-router": {
      "src": "../../node_modules/react-router/dist/development/index.mjs",
      "file": "react-router.js",
      "fileHash": "72d42a57",
      "needsInterop": false
    }
  },
  "chunks": {
    "chunk-QS7ZE27V": {
      "file": "chunk-QS7ZE27V.js"
    },
    "chunk-OBOR3357": {
      "file": "chunk-OBOR3357.js"
    }
  }
}